signalrcoreplus/__init__.py
signalrcoreplus/helpers.py
signalrcoreplus/hub_connection_builder.py
signalrcoreplus/subject.py
signalrcoreplus/hub/__init__.py
signalrcoreplus/hub/auth_hub_connection.py
signalrcoreplus/hub/base_hub_connection.py
signalrcoreplus/hub/errors.py
signalrcoreplus/hub/handlers.py
signalrcoreplus/messages/__init__.py
signalrcoreplus/messages/base_message.py
signalrcoreplus/messages/cancel_invocation_message.py
signalrcoreplus/messages/close_message.py
signalrcoreplus/messages/completion_message.py
signalrcoreplus/messages/invocation_message.py
signalrcoreplus/messages/message_type.py
signalrcoreplus/messages/ping_message.py
signalrcoreplus/messages/stream_invocation_message.py
signalrcoreplus/messages/stream_item_message.py
signalrcoreplus/messages/handshake/__init__.py
signalrcoreplus/messages/handshake/request.py
signalrcoreplus/messages/handshake/response.py
signalrcoreplus/protocol/__init__.py
signalrcoreplus/protocol/base_hub_protocol.py
signalrcoreplus/protocol/json_hub_protocol.py
signalrcoreplus/protocol/messagepack_protocol.py
signalrcoreplus/protocol/handshake/__init__.py
signalrcoreplus/transport/__init__.py
signalrcoreplus/transport/base_transport.py
signalrcoreplus/transport/websockets/__init__.py
signalrcoreplus/transport/websockets/connection.py
signalrcoreplus/transport/websockets/reconnection.py
signalrcoreplus/transport/websockets/websocket_transport.py
test/__init__.py
test/base_test_case.py
test/client_streaming_test.py
test/configuration_test.py
test/open_close_test.py
test/reconnection_test.py
test/send_auth_errors_test.py
test/send_auth_test.py
test/send_test.py
test/streaming_test.py
signalrcoreplus-0.10.3.dist-info/LICENSE
signalrcoreplus-0.10.3.dist-info/METADATA
signalrcoreplus-0.10.3.dist-info/WHEEL
signalrcoreplus-0.10.3.dist-info/top_level.txt
signalrcoreplus-0.10.3.dist-info/RECORD
