Metadata-Version: 2.1
Name: signalrcoreplus
Version: 0.10.3
Summary: A Python SignalR Core client(json and messagepack), with invocation auth and two way streaming. Compatible with azure / serverless functions. Also with automatic reconnect and manually reconnect.
Home-page: https://github.com/dcmeglio/signalrcore
Author: mandrewcito
Author-email: anbaalo@gmail.com
Keywords: signalr core client 3.1
Classifier: Programming Language :: Python :: 3.6
License-File: LICENSE
Requires-Dist: requests (>=2.22.0)
Requires-Dist: websocket-client (==1.4.2)
Requires-Dist: msgpack (==1.0.2)
